MANIFEST.in
README.md
setup.py
base/__init__.py
base/config.py
base/main.py
base/model_collections.py
base/namespace.py
base/noc.py
base/pt.py
base/qa.py
base/setup.py
base/models/__init__.py
base/models/address.py
base/models/advertisement.py
base/models/commonmodel.py
base/models/contact.py
base/models/context.py
base/models/cor.py
base/models/educationbase.py
base/models/employerbase.py
base/models/employmentbase.py
base/models/employmenthistory.py
base/models/errordict.py
base/models/family.py
base/models/finance.py
base/models/formmodel.py
base/models/id.py
base/models/jobofferbase.py
base/models/jobposition.py
base/models/language.py
base/models/m5476.py
base/models/mediaaccount.py
base/models/mixins.py
base/models/modelloader.py
base/models/person.py
base/models/phone.py
base/models/rcic.py
base/models/status.py
base/models/tr.py
base/models/trperson.py
base/models/user.py
base/models/utils.py
base/models/wordmaker.py
base/models/xmlfiller.py
base/models/xmlmaker.py
base/models/data/__init__.py
base/models/data/city.py
base/models/data/country.py
base/models/data/language.py
base/models/data/other.py
base/models/experience/__init__.py
base/models/experience/context.py
base/models/experience/data.py
base/models/experience/employmentcert.py
base/models/experience/experience.py
base/models/experience/resume.py
base/models/experience/resumedata.py
base/models/pdfform/__init__.py
base/models/pdfform/application_form.py
base/models/pdfform/config_mac.py
base/models/pdfform/config_win.py
base/models/pdfform/context.py
base/models/pdfform/fb5476.py
base/models/pdfform/form_controls_mac.py
base/models/pdfform/form_controls_win.py
base/models/pdfform/jsonmaker.py
base/models/recruit/__init__.py
base/models/recruit/context.py
base/models/recruit/jobad.py
base/models/recruit/jobaddata.py
base/models/recruit/joboffer.py
base/models/recruit/jobofferdata.py
base/models/recruit/recruitmentsummary.py
base/models/webform/__init__.py
base/models/webform/definition.py
imm_base.egg-info/PKG-INFO
imm_base.egg-info/SOURCES.txt
imm_base.egg-info/dependency_links.txt
imm_base.egg-info/entry_points.txt
imm_base.egg-info/top_level.txt